domilite/__init__.py
domilite/accessors.py
domilite/dom_tag.py
domilite/flags.py
domilite/py.typed
domilite/render.py
domilite/svg.py
domilite/tags.py
domilite/template.py
domilite/util.py
domilite-0.1.3.dist-info/METADATA
domilite-0.1.3.dist-info/WHEEL
domilite-0.1.3.dist-info/licenses/LICENSE
domilite-0.1.3.dist-info/RECORD
