Metadata-Version: 2.4
Name: domilite
Version: 0.1.3
Summary: A Python library for creating and manipulating HTML elements.
Project-URL: Documentation, https://github.com/alexrudy/domilite#readme
Project-URL: Issues, https://github.com/alexrudy/domilite/issues
Project-URL: Source, https://github.com/alexrudy/domilite
Author-email: Alex Rudy <github@alexrudy.net>
License-Expression: MIT
License-File: LICENSE
Classifier: Development Status :: 4 - Beta
Classifier: Intended Audience :: Developers
Classifier: License :: OSI Approved :: MIT License
Classifier: Operating System :: OS Independent
Classifier: Programming Language :: Python
Classifier: Topic :: Internet :: WWW/HTTP :: Dynamic Content
Classifier: Topic :: Text Processing
Classifier: Topic :: Utilities
Classifier: Typing :: Typed
Requires-Python: >=3.11
Requires-Dist: markupsafe>=3.0.2
